LICENSE
MANIFEST.in
README.rst
setup.py
easyium/__init__.py
easyium/alert.py
easyium/context.py
easyium/decorator.py
easyium/dynamic_element.py
easyium/element.py
easyium/enumeration.py
easyium/exceptions.py
easyium/identifier.py
easyium/locator.py
easyium/static_element.py
easyium/utils.py
easyium/waiter.py
easyium/web_driver.py
easyium.egg-info/PKG-INFO
easyium.egg-info/SOURCES.txt
easyium.egg-info/dependency_links.txt
easyium.egg-info/not-zip-safe
easyium.egg-info/requires.txt
easyium.egg-info/top_level.txt
examples/google.py