Metadata-Version: 1.1
Name: easyium
Version: 1.3.7
Summary: easy use of selenium and appium
Home-page: https://github.com/KarlGong/easyium-python
Author: Karl Gong
Author-email: karl.gong@outlook.com
License: Apache
Keywords: selenium appium test testing framework automation
Platform: UNKNOWN
Classifier: License :: OSI Approved :: Apache Software License
Classifier: Topic :: Software Development :: Testing
Classifier: Operating System :: Microsoft :: Windows
Classifier: Operating System :: MacOS :: MacOS X
Classifier: Programming Language :: Python :: 2.7
Classifier: Programming Language :: Python :: 3.4
Classifier: Programming Language :: Python :: 3.5
Classifier: Programming Language :: Python :: 3.6
Classifier: Programming Language :: Python :: 3.7
